kossou_hillshade_cli/__init__.py
kossou_hillshade_cli/kossou_hillshade_cli.py
kossou_hillshade_cli/version.py
kossou_hillshade_cli-0.0.5.dist-info/METADATA
kossou_hillshade_cli-0.0.5.dist-info/WHEEL
kossou_hillshade_cli-0.0.5.dist-info/entry_points.txt
kossou_hillshade_cli-0.0.5.dist-info/top_level.txt
kossou_hillshade_cli-0.0.5.dist-info/RECORD
