Metadata-Version: 2.1
Name: kossou-hillshade-cli
Version: 0.0.5
Summary: Plot hillshade over Lake Kossou using satellite elevation data
Author-email: Anthony Aylward <anthony.aylward@protonmail.com>
Project-URL: Homepage, https://https://gitlab.com/aaylward/kossou-hillshade-cli
Project-URL: Documentation, https://aaylward.gitlab.io/kossou-hillshade-cli
Classifier: Programming Language :: Python :: 3
Classifier: Operating System :: OS Independent
Classifier: License :: OSI Approved :: BSD License
Requires-Python: >=3.10
Requires-Dist: kossou-hillshade-base
Requires-Dist: misaka
